volcanoPlot/__init__.py
volcanoPlot/_modidx.py
volcanoPlot/volcano.py
volcanoPlot-0.0.2.dist-info/LICENSE
volcanoPlot-0.0.2.dist-info/METADATA
volcanoPlot-0.0.2.dist-info/WHEEL
volcanoPlot-0.0.2.dist-info/entry_points.txt
volcanoPlot-0.0.2.dist-info/top_level.txt
volcanoPlot-0.0.2.dist-info/RECORD
