Metadata-Version: 2.1
Name: volcanoPlot
Version: 0.0.2
Summary: creating a volcano plot in python for the given data, and save it as a png file.
Home-page: https://github.com/avivleemann/volcanoPlot
Author: avivleemann
Author-email: avivleemann@gmail.com
License: Apache Software License 2.0
Keywords: nbdev jupyter notebook python
Classifier: Development Status :: 4 - Beta
Classifier: Intended Audience :: Developers
Classifier: Natural Language :: English
Classifier: Programming Language :: Python :: 3.7
Classifier: Programming Language :: Python :: 3.8
Classifier: Programming Language :: Python :: 3.9
Classifier: Programming Language :: Python :: 3.10
Classifier: License :: OSI Approved :: Apache Software License
Requires-Python: >=3.7
License-File: LICENSE
Requires-Dist: matplotlib
Requires-Dist: pandas
Requires-Dist: numpy
Requires-Dist: pathlib
Requires-Dist: typing
Requires-Dist: adjustText
Provides-Extra: dev
